[
  {
    "hanreiId": "95340",
    "detailType": "2",
    "caseNumber": "令和6(受)1046",
    "caseName": "建物明渡等請求本訴、損害賠償請求反訴事件",
    "date": "令和8年1月9日",
    "court": "最高裁判所",
    "division": "第二小法廷",
    "judgeKind": "判決",
    "outcome": "棄却",
    "genshinCourt": "仙台高等裁判所",
    "genshinCaseNumber": "令和5(ネ)44",
    "field": "民事",
    "fullTextPdf": "https://www.courts.go.jp/assets/hanrei/hanrei-pdf-95340.pdf",
    "detailUrl": "https://www.courts.go.jp/hanrei/95340/detail2/index.html",
    "needsReview": false,
    "unanimous": false,
    "individualOpinions": [
      {
        "judge": "高須順一",
        "opinionType": "意見",
        "bodyLength": 4319,
        "judgeId": "takasu"
      },
      {
        "judge": "三浦守",
        "opinionType": "反対意見",
        "bodyLength": 14868,
        "judgeId": "miura"
      }
    ],
    "pdfTextLength": 23371
  },
  {
    "hanreiId": "95373",
    "detailType": "2",
    "caseNumber": "令和6(あ)1087",
    "caseName": "窃盗被告事件",
    "date": "令和8年1月14日",
    "court": "最高裁判所",
    "division": "第三小法廷",
    "judgeKind": "決定",
    "outcome": "棄却",
    "genshinCourt": "名古屋高等裁判所",
    "genshinCaseNumber": "令和6(う)97",
    "field": "刑事",
    "fullTextPdf": "https://www.courts.go.jp/assets/hanrei/hanrei-pdf-95373.pdf",
    "detailUrl": "https://www.courts.go.jp/hanrei/95373/detail2/index.html",
    "needsReview": false,
    "unanimous": false,
    "individualOpinions": [],
    "pdfTextLength": 1717
  },
  {
    "hanreiId": "95385",
    "detailType": "2",
    "caseNumber": "令和5(受)2245",
    "caseName": "第三者異議事件",
    "date": "令和8年1月20日",
    "court": "最高裁判所",
    "division": "第三小法廷",
    "judgeKind": "判決",
    "outcome": "破棄差戻",
    "genshinCourt": "東京高等裁判所",
    "genshinCaseNumber": "令和5(ネ)2021",
    "field": "民事",
    "fullTextPdf": "https://www.courts.go.jp/assets/hanrei/hanrei-pdf-95385.pdf",
    "detailUrl": "https://www.courts.go.jp/hanrei/95385/detail2/index.html",
    "needsReview": false,
    "unanimous": true,
    "individualOpinions": [
      {
        "judge": "沖野眞已",
        "opinionType": "意見",
        "bodyLength": 3191,
        "judgeId": "okino"
      }
    ],
    "pdfTextLength": 8714
  },
  {
    "hanreiId": "95402",
    "detailType": "2",
    "caseNumber": "令和6(受)385",
    "caseName": "損害賠償等請求事件",
    "date": "令和8年1月22日",
    "court": "最高裁判所",
    "division": "第一小法廷",
    "judgeKind": "判決",
    "outcome": null,
    "genshinCourt": "東京高等裁判所",
    "genshinCaseNumber": "令和5(ネ)786",
    "field": "民事",
    "fullTextPdf": "https://www.courts.go.jp/assets/hanrei/hanrei-pdf-95402.pdf",
    "detailUrl": "https://www.courts.go.jp/hanrei/95402/detail2/index.html",
    "needsReview": false,
    "unanimous": true,
    "individualOpinions": [],
    "pdfTextLength": 2435
  },
  {
    "hanreiId": "95412",
    "detailType": "2",
    "caseNumber": "令和5(行ヒ)339",
    "caseName": "固定資産税及び都市計画税賦課決定処分取消請求事件",
    "date": "令和8年1月26日",
    "court": "最高裁判所",
    "division": "第二小法廷",
    "judgeKind": "判決",
    "outcome": "破棄自判",
    "genshinCourt": "大阪高等裁判所",
    "genshinCaseNumber": "令和4(行コ)164",
    "field": "行政",
    "fullTextPdf": "https://www.courts.go.jp/assets/hanrei/hanrei-pdf-95412.pdf",
    "detailUrl": "https://www.courts.go.jp/hanrei/95412/detail2/index.html",
    "needsReview": false,
    "unanimous": true,
    "individualOpinions": [
      {
        "judge": "三浦守",
        "opinionType": "補足意見",
        "bodyLength": 1771,
        "judgeId": "miura"
      },
      {
        "judge": "高須順一",
        "opinionType": "反対意見",
        "bodyLength": 3022,
        "judgeId": "takasu"
      }
    ],
    "pdfTextLength": 7906
  },
  {
    "hanreiId": "95429",
    "detailType": "2",
    "caseNumber": "令和7(行ツ)72",
    "caseName": "行政文書不開示決定取消請求事件",
    "date": "令和8年1月27日",
    "court": "最高裁判所",
    "division": "第三小法廷",
    "judgeKind": "判決",
    "outcome": "破棄差戻",
    "genshinCourt": "名古屋高等裁判所",
    "genshinCaseNumber": "令和6(行コ)46",
    "field": "行政",
    "fullTextPdf": "https://www.courts.go.jp/assets/hanrei/hanrei-pdf-95429.pdf",
    "detailUrl": "https://www.courts.go.jp/hanrei/95429/detail2/index.html",
    "needsReview": false,
    "unanimous": true,
    "individualOpinions": [],
    "pdfTextLength": 1308
  },
  {
    "hanreiId": "95466",
    "detailType": "2",
    "caseNumber": "令和7(マ)244",
    "caseName": "離婚等請求事件",
    "date": "令和8年1月28日",
    "court": "最高裁判所",
    "division": "第一小法廷",
    "judgeKind": "決定",
    "outcome": "却下",
    "genshinCourt": null,
    "genshinCaseNumber": null,
    "field": "民事",
    "fullTextPdf": "https://www.courts.go.jp/assets/hanrei/hanrei-pdf-95466.pdf",
    "detailUrl": "https://www.courts.go.jp/hanrei/95466/detail2/index.html",
    "needsReview": false,
    "unanimous": true,
    "individualOpinions": [],
    "pdfTextLength": 2343
  },
  {
    "hanreiId": "95467",
    "detailType": "2",
    "caseNumber": "令和7(許)18",
    "caseName": "再審却下決定に対する抗告許可申立事件",
    "date": "令和8年1月28日",
    "court": "最高裁判所",
    "division": "第一小法廷",
    "judgeKind": "決定",
    "outcome": "却下",
    "genshinCourt": null,
    "genshinCaseNumber": null,
    "field": "民事",
    "fullTextPdf": "https://www.courts.go.jp/assets/hanrei/hanrei-pdf-95467.pdf",
    "detailUrl": "https://www.courts.go.jp/hanrei/95467/detail2/index.html",
    "needsReview": false,
    "unanimous": true,
    "individualOpinions": [],
    "pdfTextLength": 1851
  },
  {
    "hanreiId": "95523",
    "detailType": "2",
    "caseNumber": "令和6(受)2399",
    "caseName": "労働契約法20条違反による損害賠償請求事件",
    "date": "令和8年2月13日",
    "court": "最高裁判所",
    "division": "第二小法廷",
    "judgeKind": "判決",
    "outcome": null,
    "genshinCourt": "名古屋高等裁判所",
    "genshinCaseNumber": "令和5(ネ)360",
    "field": "民事",
    "fullTextPdf": "https://www.courts.go.jp/assets/hanrei/hanrei-pdf-95523.pdf",
    "detailUrl": "https://www.courts.go.jp/hanrei/95523/detail2/index.html",
    "needsReview": false,
    "unanimous": true,
    "individualOpinions": [],
    "pdfTextLength": 2162
  },
  {
    "hanreiId": "95548",
    "detailType": "2",
    "caseNumber": "令和5(オ)360",
    "caseName": "地位確認等請求事件",
    "date": "令和8年2月18日",
    "court": "最高裁判所",
    "division": "大法廷",
    "judgeKind": "判決",
    "outcome": "破棄自判",
    "genshinCourt": "名古屋高等裁判所",
    "genshinCaseNumber": "令和3(ネ)833",
    "field": "民事",
    "fullTextPdf": "https://www.courts.go.jp/assets/hanrei/hanrei-pdf-95548.pdf",
    "detailUrl": "https://www.courts.go.jp/hanrei/95548/detail2/index.html",
    "needsReview": true,
    "unanimous": true,
    "individualOpinions": [
      {
        "judge": "林道晴",
        "opinionType": "補足意見",
        "bodyLength": 2423,
        "judgeId": "hayashi_m"
      },
      {
        "judge": "岡正晶",
        "opinionType": "補足意見",
        "bodyLength": 4316,
        "judgeId": null
      },
      {
        "judge": "石兼公博",
        "opinionType": "補足意見",
        "bodyLength": 3256,
        "judgeId": "ishikane"
      },
      {
        "judge": "安浪亮介",
        "opinionType": "意見",
        "bodyLength": 4784,
        "judgeId": "yasunami"
      },
      {
        "judge": "三浦守",
        "opinionType": "反対意見",
        "bodyLength": 17829,
        "judgeId": "miura"
      },
      {
        "judge": "尾島明",
        "opinionType": "反対意見",
        "bodyLength": 9345,
        "judgeId": "ojima"
      },
      {
        "judge": "宮川美津子",
        "opinionType": "反対意見",
        "bodyLength": 12077,
        "judgeId": "miyagawa"
      },
      {
        "judge": "高須順一",
        "opinionType": "反対意見",
        "bodyLength": 7622,
        "judgeId": "takasu"
      },
      {
        "judge": "沖野眞已",
        "opinionType": "反対意見",
        "bodyLength": 11892,
        "judgeId": "okino"
      }
    ],
    "pdfTextLength": 89424
  },
  {
    "hanreiId": "95570",
    "detailType": "2",
    "caseNumber": "令和6(行ヒ)362",
    "caseName": "保有個人情報不開示決定処分取消請求事件",
    "date": "令和8年2月20日",
    "court": "最高裁判所",
    "division": "第三小法廷",
    "judgeKind": "判決",
    "outcome": "棄却",
    "genshinCourt": "大阪高等裁判所",
    "genshinCaseNumber": "令和6(行コ)17",
    "field": "行政",
    "fullTextPdf": "https://www.courts.go.jp/assets/hanrei/hanrei-pdf-95570.pdf",
    "detailUrl": "https://www.courts.go.jp/hanrei/95570/detail2/index.html",
    "needsReview": false,
    "unanimous": true,
    "individualOpinions": [],
    "pdfTextLength": 5306
  },
  {
    "hanreiId": "95593",
    "detailType": "2",
    "caseNumber": "令和5(し)155",
    "caseName": "再審開始決定に対する即時抗告棄却決定に対する特別抗告事件",
    "date": "令和8年2月24日",
    "court": "最高裁判所",
    "division": "第二小法廷",
    "judgeKind": "決定",
    "outcome": "棄却",
    "genshinCourt": "大阪高等裁判所",
    "genshinCaseNumber": "平成30(く)251",
    "field": "刑事",
    "fullTextPdf": "https://www.courts.go.jp/assets/hanrei/hanrei-pdf-95593.pdf",
    "detailUrl": "https://www.courts.go.jp/hanrei/95593/detail2/index.html",
    "needsReview": false,
    "unanimous": true,
    "individualOpinions": [],
    "pdfTextLength": 428
  },
  {
    "hanreiId": "95768",
    "detailType": "2",
    "caseNumber": "令和7(行ヒ)25",
    "caseName": "行政処分取消請求事件",
    "date": "令和8年3月27日",
    "court": "最高裁判所",
    "division": "第三小法廷",
    "judgeKind": "判決",
    "outcome": "破棄自判",
    "genshinCourt": "札幌高等裁判所",
    "genshinCaseNumber": "令和4(行コ)1",
    "field": "行政",
    "fullTextPdf": "https://www.courts.go.jp/assets/hanrei/hanrei-pdf-95768.pdf",
    "detailUrl": "https://www.courts.go.jp/hanrei/95768/detail2/index.html",
    "needsReview": true,
    "unanimous": true,
    "individualOpinions": [
      {
        "judge": "林道晴",
        "opinionType": "補足意見",
        "bodyLength": 2153,
        "judgeId": "hayashi_m"
      },
      {
        "judge": "渡辺惠理子",
        "opinionType": "意見",
        "bodyLength": 3568,
        "judgeId": null
      }
    ],
    "pdfTextLength": 13284
  },
  {
    "hanreiId": "95801",
    "detailType": "2",
    "caseNumber": "令和8(し)235",
    "caseName": "勾留の裁判に対する準抗告棄却決定に対する特別抗告事件",
    "date": "令和8年4月1日",
    "court": "最高裁判所",
    "division": "第二小法廷",
    "judgeKind": "決定",
    "outcome": "棄却",
    "genshinCourt": "福岡地方裁判所",
    "genshinCaseNumber": "令和8(む)50043",
    "field": "刑事",
    "fullTextPdf": "https://www.courts.go.jp/assets/hanrei/hanrei-pdf-95801.pdf",
    "detailUrl": "https://www.courts.go.jp/hanrei/95801/detail2/index.html",
    "needsReview": false,
    "unanimous": true,
    "individualOpinions": [],
    "pdfTextLength": 1492
  },
  {
    "hanreiId": "95816",
    "detailType": "2",
    "caseNumber": "令和6(あ)1479",
    "caseName": "各廃棄物の処理及び清掃に関する法律違反被告事件",
    "date": "令和8年4月7日",
    "court": "最高裁判所",
    "division": "第三小法廷",
    "judgeKind": "決定",
    "outcome": "棄却",
    "genshinCourt": "東京高等裁判所",
    "genshinCaseNumber": "令和5(う)1193",
    "field": "刑事",
    "fullTextPdf": "https://www.courts.go.jp/assets/hanrei/hanrei-pdf-95816.pdf",
    "detailUrl": "https://www.courts.go.jp/hanrei/95816/detail2/index.html",
    "needsReview": false,
    "unanimous": false,
    "individualOpinions": [],
    "pdfTextLength": 3558
  },
  {
    "hanreiId": "95900",
    "detailType": "2",
    "caseNumber": "令和6(あ)1657",
    "caseName": "入札談合等関与行為の排除及び防止並びに職員による入札等の公正を害すべき行為の処罰に関する法律違反、公契約関係競売入札妨害被告事件",
    "date": "令和8年4月21日",
    "court": "最高裁判所",
    "division": "第三小法廷",
    "judgeKind": "決定",
    "outcome": "棄却",
    "genshinCourt": null,
    "genshinCaseNumber": null,
    "field": "刑事",
    "fullTextPdf": "https://www.courts.go.jp/assets/hanrei/hanrei-pdf-95900.pdf",
    "detailUrl": "https://www.courts.go.jp/hanrei/95900/detail2/index.html",
    "needsReview": false,
    "unanimous": true,
    "individualOpinions": [],
    "pdfTextLength": 2481
  },
  {
    "hanreiId": "95904",
    "detailType": "2",
    "caseNumber": "令和7(受)356",
    "caseName": "不正競争行為差止等請求事件",
    "date": "令和8年4月24日",
    "court": "最高裁判所",
    "division": "第二小法廷",
    "judgeKind": "判決",
    "outcome": "棄却",
    "genshinCourt": "知的財産高等裁判所",
    "genshinCaseNumber": "令和5(ネ)10111",
    "field": "民事",
    "fullTextPdf": "https://www.courts.go.jp/assets/hanrei/hanrei-pdf-95904.pdf",
    "detailUrl": "https://www.courts.go.jp/hanrei/95904/detail2/index.html",
    "needsReview": true,
    "unanimous": true,
    "individualOpinions": [
      {
        "judge": "尾島明",
        "opinionType": "補足意見",
        "bodyLength": 2859,
        "judgeId": "ojima"
      }
    ],
    "pdfTextLength": 6432
  },
  {
    "hanreiId": "96022",
    "detailType": "2",
    "caseNumber": "令和8(し)416",
    "caseName": "接見等禁止の裁判に対する準抗告棄却決定に対する特別抗告事件",
    "date": "令和8年5月27日",
    "court": "最高裁判所",
    "division": "第二小法廷",
    "judgeKind": "決定",
    "outcome": "棄却",
    "genshinCourt": "東京地方裁判所",
    "genshinCaseNumber": "令和8(む)95078",
    "field": "刑事",
    "fullTextPdf": "https://www.courts.go.jp/assets/hanrei/hanrei-pdf-96022.pdf",
    "detailUrl": "https://www.courts.go.jp/hanrei/96022/detail2/index.html",
    "needsReview": false,
    "unanimous": true,
    "individualOpinions": [],
    "pdfTextLength": 625
  },
  {
    "hanreiId": "96035",
    "detailType": "2",
    "caseNumber": "令和8(し)378",
    "caseName": "保釈取消し決定及び保釈保証金の全部を没取する決定に対する抗告棄却決定に対する特別抗告事件",
    "date": "令和8年5月29日",
    "court": "最高裁判所",
    "division": "第三小法廷",
    "judgeKind": "決定",
    "outcome": "棄却",
    "genshinCourt": "東京高等裁判所",
    "genshinCaseNumber": "令和8(く)261",
    "field": "刑事",
    "fullTextPdf": "https://www.courts.go.jp/assets/hanrei/hanrei-pdf-96035.pdf",
    "detailUrl": "https://www.courts.go.jp/hanrei/96035/detail2/index.html",
    "needsReview": false,
    "unanimous": true,
    "individualOpinions": [],
    "pdfTextLength": 894
  },
  {
    "hanreiId": "96050",
    "detailType": "2",
    "caseNumber": "令和8(行フ)1",
    "caseName": "難民審査請求棄却裁決効力停止決定に対する抗告棄却決定に対する許可抗告事件",
    "date": "令和8年5月27日",
    "court": "最高裁判所",
    "division": "第二小法廷",
    "judgeKind": "決定",
    "outcome": "棄却",
    "genshinCourt": "東京高等裁判所",
    "genshinCaseNumber": "令和7(行ス)99",
    "field": "行政",
    "fullTextPdf": "https://www.courts.go.jp/assets/hanrei/hanrei-pdf-96050.pdf",
    "detailUrl": "https://www.courts.go.jp/hanrei/96050/detail2/index.html",
    "needsReview": false,
    "unanimous": true,
    "individualOpinions": [],
    "pdfTextLength": 749
  }
]